fs_s3fs/__init__.py
fs_s3fs/_s3fs.py
fs_s3fs/_version.py
fs_s3fs/opener.py
fs_s3fs-1.1.0.dist-info/DESCRIPTION.rst
fs_s3fs-1.1.0.dist-info/METADATA
fs_s3fs-1.1.0.dist-info/RECORD
fs_s3fs-1.1.0.dist-info/WHEEL
fs_s3fs-1.1.0.dist-info/entry_points.txt
fs_s3fs-1.1.0.dist-info/metadata.json
fs_s3fs-1.1.0.dist-info/top_level.txt
