Metadata-Version: 2.0
Name: fs-s3fs
Version: 1.1.0
Summary: Amazon S3 filesystem for PyFilesystem2
Home-page: https://github.com/PyFilesystem/s3fs
Author: Will McGugan
Author-email: willmcgugan@gmail.com
License: MIT
Keywords: pyfilesystem,Amazon,s3
Platform: any
Classifier: Development Status :: 4 - Beta
Classifier: Intended Audience :: Developers
Classifier: License :: OSI Approved :: MIT License
Classifier: Operating System :: OS Independent
Classifier: Programming Language :: Python
Classifier: Programming Language :: Python :: 2.7
Classifier: Programming Language :: Python :: 3.3
Classifier: Programming Language :: Python :: 3.4
Classifier: Programming Language :: Python :: 3.5
Classifier: Programming Language :: Python :: 3.6
Classifier: Programming Language :: Python :: 3.7
Classifier: Topic :: System :: Filesystems
Requires-Dist: boto3 (~=1.7)
Requires-Dist: fs (~=2.2)
Requires-Dist: six (~=1.10)
